setup.py
eodclient/__init__.py
eodclient/errors.py
eodclient/exchange.py
eodclient/symbol.py
eodclient.egg-info/PKG-INFO
eodclient.egg-info/SOURCES.txt
eodclient.egg-info/dependency_links.txt
eodclient.egg-info/requires.txt
eodclient.egg-info/top_level.txt