Metadata-Version: 1.2
Name: eodclient
Version: 1.1.3.dev1
Summary: A python client for interacting with the EOD Historical Data api
Home-page: https://github.com/surfer190/EOD-Historical-Data-client
Author: surfer190
Author-email: shutch190@gmail.com
License: GPLv3
Download-URL: https://github.com/surfer190/EOD-Historical-Data-client/archive/1.1.3.dev1.tar.gz
Keywords: api,client,eod
Platform: UNKNOWN
Requires-Python: >=3.6
